{"stocks": [{"Ticker": "UCO", "Price": 38.54, "Today %": 0.68, "3D %": 12.49, "5D %": 14.77, "15D %": 54.84, "Dollar Volume": 469718973.5772915, "Above MA20": true, "Above MA50": true, "Vol Surge": 2.37, "Acceleration": true, "Breakout": true, "Near High": true, "ChangeOpenUp": true, "Today vs": 6.35, "5D vs": 9.33, "15D vs": 79.6, "Composite Score": 167.1, "Name": "ProShares Ultra Bloomberg Crude"}, {"Ticker": "CF", "Price": 132.61, "Today %": 3.59, "3D %": 20.5, "5D %": 14.54, "15D %": 36.46, "Dollar Volume": 585086176.821421, "Above MA20": true, "Above MA50": true, "Vol Surge": 1.63, "Acceleration": true, "Breakout": true, "Near High": true, "ChangeOpenUp": true, "Today vs": 9.26, "5D vs": 9.1, "15D vs": 61.22, "Composite Score": 152.31, "Name": "CF Industries Holdings, Inc."}, {"Ticker": "FLY", "Price": 23.62, "Today %": -0.35, "3D %": 21.81, "5D %": 19.71, "15D %": 18.21, "Dollar Volume": 60615400.52356224, "Above MA20": true, "Above MA50": false, "Vol Surge": 1.18, "Acceleration": true, "Breakout": true, "Near High": true, "ChangeOpenUp": false, "Today vs": 5.32, "5D vs": 14.27, "15D vs": 42.97, "Composite Score": 137.62, "Name": "Firefly Aerospace Inc."}, {"Ticker": "UMAC", "Price": 21.0, "Today %": 4.97, "3D %": 13.54, "5D %": 27.69, "15D %": 56.29, "Dollar Volume": 73338751.87157468, "Above MA20": true, "Above MA50": true, "Vol Surge": 1.84, "Acceleration": false, "Breakout": true, "Near High": true, "ChangeOpenUp": true, "Today vs": 10.64, "5D vs": 22.25, "15D vs": 81.05, "Composite Score": 125.55, "Name": "Unusual Machines, Inc."}, {"Ticker": "MOS", "Price": 31.37, "Today %": 1.03, "3D %": 18.47, "5D %": 20.24, "15D %": 7.49, "Dollar Volume": 253311892.53328657, "Above MA20": true, "Above MA50": true, "Vol Surge": 1.29, "Acceleration": true, "Breakout": true, "Near High": true, "ChangeOpenUp": true, "Today vs": 6.7, "5D vs": 14.8, "15D vs": 32.25, "Composite Score": 121.82, "Name": "Mosaic Company (The)"}, {"Ticker": "DOW", "Price": 37.21, "Today %": 4.08, "3D %": 9.8, "5D %": 11.81, "15D %": 23.36, "Dollar Volume": 521575368.3824841, "Above MA20": true, "Above MA50": true, "Vol Surge": 1.27, "Acceleration": true, "Breakout": true, "Near High": true, "ChangeOpenUp": true, "Today vs": 9.75, "5D vs": 6.37, "15D vs": 48.12, "Composite Score": 115.17, "Name": "Dow Inc."}, {"Ticker": "PARR", "Price": 53.59, "Today %": 3.54, "3D %": 11.58, "5D %": 9.66, "15D %": 25.36, "Dollar Volume": 72203366.67458612, "Above MA20": true, "Above MA50": true, "Vol Surge": 0.92, "Acceleration": true, "Breakout": false, "Near High": true, "ChangeOpenUp": true, "Today vs": 9.21, "5D vs": 4.22, "15D vs": 50.12, "Composite Score": 110.08, "Name": "Par Pacific Holdings, Inc. Comm"}, {"Ticker": "SOC", "Price": 17.35, "Today %": 2.06, "3D %": 20.4, "5D %": 20.74, "15D %": 93.85, "Dollar Volume": 121754170.73197575, "Above MA20": true, "Above MA50": true, "Vol Surge": 1.45, "Acceleration": true, "Breakout": true, "Near High": true, "ChangeOpenUp": true, "Today vs": 7.73, "5D vs": 15.3, "15D vs": 118.61, "Composite Score": 109.16, "Name": "Sable Offshore Corp."}, {"Ticker": "PUMP", "Price": 13.69, "Today %": 4.74, "3D %": 12.21, "5D %": 10.4, "15D %": 21.8, "Dollar Volume": 41835134.87119746, "Above MA20": true, "Above MA50": true, "Vol Surge": 0.87, "Acceleration": true, "Breakout": false, "Near High": true, "ChangeOpenUp": true, "Today vs": 10.41, "5D vs": 4.96, "15D vs": 46.56, "Composite Score": 108.16, "Name": "ProPetro Holding Corp."}, {"Ticker": "NTR", "Price": 84.26, "Today %": 2.59, "3D %": 10.74, "5D %": 10.56, "15D %": 18.34, "Dollar Volume": 308828841.39568865, "Above MA20": true, "Above MA50": true, "Vol Surge": 1.43, "Acceleration": true, "Breakout": true, "Near High": true, "ChangeOpenUp": true, "Today vs": 8.26, "5D vs": 5.12, "15D vs": 43.1, "Composite Score": 106.99, "Name": "Nutrien Ltd."}, {"Ticker": "USO", "Price": 116.38, "Today %": 0.6, "3D %": 9.94, "5D %": 7.0, "15D %": 43.95, "Dollar Volume": 4238946247.098093, "Above MA20": true, "Above MA50": true, "Vol Surge": 2.48, "Acceleration": true, "Breakout": true, "Near High": true, "ChangeOpenUp": true, "Today vs": 6.27, "5D vs": 1.56, "15D vs": 68.71, "Composite Score": 101.39, "Name": "United States Oil Fund"}, {"Ticker": "BNO", "Price": 47.58, "Today %": 0.66, "3D %": 9.71, "5D %": 8.26, "15D %": 40.44, "Dollar Volume": 235336572.3236229, "Above MA20": true, "Above MA50": true, "Vol Surge": 2.29, "Acceleration": true, "Breakout": true, "Near High": true, "ChangeOpenUp": true, "Today vs": 6.33, "5D vs": 2.82, "15D vs": 65.2, "Composite Score": 99.2, "Name": "United States Brent Oil Fund, L"}, {"Ticker": "DBO", "Price": 20.03, "Today %": 0.3, "3D %": 8.09, "5D %": 9.69, "15D %": 40.76, "Dollar Volume": 44554494.16886606, "Above MA20": true, "Above MA50": true, "Vol Surge": 2.31, "Acceleration": true, "Breakout": true, "Near High": true, "ChangeOpenUp": true, "Today vs": 5.97, "5D vs": 4.25, "15D vs": 65.52, "Composite Score": 98.13, "Name": "Invesco DB Oil Fund"}, {"Ticker": "FAZ", "Price": 53.32, "Today %": 0.74, "3D %": 6.94, "5D %": 10.32, "15D %": 22.27, "Dollar Volume": 58931681.40991516, "Above MA20": true, "Above MA50": true, "Vol Surge": 0.83, "Acceleration": true, "Breakout": false, "Near High": true, "ChangeOpenUp": true, "Today vs": 6.41, "5D vs": 4.88, "15D vs": 47.03, "Composite Score": 91.2, "Name": "Direxion Financial Bear 3X Shar"}, {"Ticker": "XPEV", "Price": 19.93, "Today %": 1.76, "3D %": 5.64, "5D %": 15.1, "15D %": 13.14, "Dollar Volume": 110662370.63861075, "Above MA20": true, "Above MA50": true, "Vol Surge": 1.49, "Acceleration": false, "Breakout": true, "Near High": true, "ChangeOpenUp": true, "Today vs": 7.43, "5D vs": 9.66, "15D vs": 37.9, "Composite Score": 80.49, "Name": "XPeng Inc."}], "etfs": [{"Ticker": "UCO", "Price": 38.54, "Today %": 0.68, "3D %": 12.49, "5D %": 14.77, "15D %": 54.84, "Dollar Volume": 469718973.5772915, "Above MA20": true, "Above MA50": true, "Vol Surge": 2.37, "Acceleration": true, "Breakout": true, "Near High": true, "ChangeOpenUp": true, "Today vs": 1.35, "5D vs": 14.94, "15D vs": 56.5, "Composite Score": 163.91, "Name": "ProShares Ultra Bloomberg Crude"}, {"Ticker": "USO", "Price": 116.47, "Today %": 0.67, "3D %": 10.02, "5D %": 7.08, "15D %": 44.06, "Dollar Volume": 4241988098.404587, "Above MA20": true, "Above MA50": true, "Vol Surge": 2.48, "Acceleration": true, "Breakout": true, "Near High": true, "ChangeOpenUp": true, "Today vs": 1.34, "5D vs": 7.25, "15D vs": 45.72, "Composite Score": 97.04, "Name": "United States Oil Fund"}, {"Ticker": "BNO", "Price": 47.61, "Today %": 0.72, "3D %": 9.78, "5D %": 8.33, "15D %": 40.53, "Dollar Volume": 235482812.3063469, "Above MA20": true, "Above MA50": true, "Vol Surge": 2.29, "Acceleration": true, "Breakout": true, "Near High": true, "ChangeOpenUp": true, "Today vs": 1.39, "5D vs": 8.5, "15D vs": 42.19, "Composite Score": 94.77, "Name": "United States Brent Oil Fund, L"}, {"Ticker": "GUSH", "Price": 37.6, "Today %": 1.33, "3D %": 10.96, "5D %": 4.05, "15D %": 20.92, "Dollar Volume": 71520843.33538055, "Above MA20": true, "Above MA50": true, "Vol Surge": 1.36, "Acceleration": true, "Breakout": true, "Near High": true, "ChangeOpenUp": true, "Today vs": 2.0, "5D vs": 4.22, "15D vs": 22.58, "Composite Score": 65.15, "Name": "Direxion Daily S&P Oil & Gas Ex"}, {"Ticker": "ERX", "Price": 91.05, "Today %": 1.57, "3D %": 7.44, "5D %": 3.8, "15D %": 9.74, "Dollar Volume": 65550437.06851959, "Above MA20": true, "Above MA50": true, "Vol Surge": 1.34, "Acceleration": true, "Breakout": true, "Near High": true, "ChangeOpenUp": true, "Today vs": 2.24, "5D vs": 3.97, "15D vs": 11.4, "Composite Score": 54.98, "Name": "Direxion Energy Bull 2X Shares"}, {"Ticker": "SOXL", "Price": 50.47, "Today %": -5.73, "3D %": -7.56, "5D %": 5.38, "15D %": -24.8, "Dollar Volume": 4256246799.6986, "Above MA20": false, "Above MA50": false, "Vol Surge": 1.09, "Acceleration": false, "Breakout": false, "Near High": false, "ChangeOpenUp": false, "Today vs": -5.06, "5D vs": 5.55, "15D vs": -23.14, "Composite Score": -14.81, "Name": "Direxion Daily Semiconductor Bu"}]}