{"stocks": [{"Ticker": "QURE", "Price": 47.19, "ATR": 3.92, "ATR %": 8.31, "Today %": 6.31, "3D %": 1.94, "5D %": 74.84, "15D %": 76.35, "13W %": 219.5, "MA20": 30.93, "MA50": 25.32, "MA200": 27.81, "MA50 Rising": true, "Above 200MA": true, "Above MA20": true, "Trend Quality": true, "Extension %": 86.35, "Overextended": true, "Drawdown %": -2.01, "Stop Triggered": false, "Hard Stop Triggered": false, "Hard Stop %": 12.0, "Stop Threshold": 20.36, "Vol Surge": 2.28, "Acceleration": false, "Breakout": false, "Near High": false, "Dollar Volume": 121025589.3089962, "Leveraged": false, "TV_Oscillators": "NEUTRAL", "TV_MovingAverages": "BUY", "TV_RSI": 77.12, "TV_MACD": 2.0632, "Entry Quality": "MOMENTUM", "Short Interest": 0.17860001, "Days To Cover": 0, "Squeeze Score": 0, "Score": 267.99, "Name": "uniQure N.V.", "osc_buy": 3, "osc_sell": 3, "osc_neutral": 0, "ma_buy": 8, "ma_sell": 0, "ma_neutral": 0}, {"Ticker": "ARQQ", "Price": 27.6, "ATR": 3.05, "ATR %": 11.04, "Today %": 28.87, "3D %": 13.23, "5D %": 38.44, "15D %": 69.67, "13W %": 134.34, "MA20": 16.99, "MA50": 15.58, "MA200": 24.3, "MA50 Rising": true, "Above 200MA": true, "Above MA20": true, "Trend Quality": true, "Extension %": 77.14, "Overextended": true, "Drawdown %": -0.99, "Stop Triggered": false, "Hard Stop Triggered": false, "Hard Stop %": 12.0, "Stop Threshold": 27.32, "Vol Surge": 2.16, "Acceleration": false, "Breakout": true, "Near High": true, "Dollar Volume": 36960249.691851616, "Leveraged": false, "TV_Oscillators": "NEUTRAL", "TV_MovingAverages": "BUY", "TV_RSI": 71.5, "TV_MACD": 1.2888, "Entry Quality": "MOMENTUM", "Short Interest": 0.1346, "Days To Cover": 0, "Squeeze Score": 0, "Score": 206.41, "Name": "Arqit Quantum Inc.", "osc_buy": 3, "osc_sell": 3, "osc_neutral": 0, "ma_buy": 8, "ma_sell": 0, "ma_neutral": 0}, {"Ticker": "APGE", "Price": 132.85, "ATR": 7.64, "ATR %": 5.75, "Today %": 0.23, "3D %": 46.99, "5D %": 55.85, "15D %": 68.78, "13W %": 70.71, "MA20": 89.24, "MA50": 86.61, "MA200": 70.33, "MA50 Rising": true, "Above 200MA": true, "Above MA20": true, "Trend Quality": true, "Extension %": 53.38, "Overextended": true, "Drawdown %": 0.0, "Stop Triggered": false, "Hard Stop Triggered": false, "Hard Stop %": 12.0, "Stop Threshold": 14.38, "Vol Surge": 3.18, "Acceleration": true, "Breakout": true, "Near High": true, "Dollar Volume": 599020737.3032547, "Leveraged": false, "TV_Oscillators": "NEUTRAL", "TV_MovingAverages": "BUY", "TV_RSI": 82.61, "TV_MACD": 4.8879, "Entry Quality": "MOMENTUM", "Short Interest": 0.2201, "Days To Cover": 0, "Squeeze Score": 0, "Score": 300, "Name": "Apogee Therapeutics, Inc.", "osc_buy": 3, "osc_sell": 3, "osc_neutral": 0, "ma_buy": 8, "ma_sell": 0, "ma_neutral": 0}, {"Ticker": "DFTX", "Price": 37.87, "ATR": 2.69, "ATR %": 7.1, "Today %": 3.27, "3D %": 54.7, "5D %": 56.75, "15D %": 65.66, "13W %": 111.8, "MA20": 25.11, "MA50": 23.24, "MA200": 16.57, "MA50 Rising": true, "Above 200MA": true, "Above MA20": true, "Trend Quality": true, "Extension %": 62.95, "Overextended": true, "Drawdown %": 0.0, "Stop Triggered": false, "Hard Stop Triggered": false, "Hard Stop %": 12.0, "Stop Threshold": 17.76, "Vol Surge": 1.8, "Acceleration": true, "Breakout": true, "Near High": true, "Dollar Volume": 121365719.3088295, "Leveraged": false, "TV_Oscillators": "NEUTRAL", "TV_MovingAverages": "BUY", "TV_RSI": 87.06, "TV_MACD": 1.3191, "Entry Quality": "MOMENTUM", "Short Interest": 0.0871, "Days To Cover": 0, "Squeeze Score": 0, "Score": 300, "Name": "Definium Therapeutics, Inc.", "osc_buy": 3, "osc_sell": 3, "osc_neutral": 0, "ma_buy": 8, "ma_sell": 0, "ma_neutral": 0}, {"Ticker": "OSCR", "Price": 28.93, "ATR": 1.87, "ATR %": 6.46, "Today %": 1.37, "3D %": 1.87, "5D %": 1.3, "15D %": 36.85, "13W %": 159.69, "MA20": 25.63, "MA50": 21.9, "MA200": 17.47, "MA50 Rising": true, "Above 200MA": true, "Above MA20": true, "Trend Quality": true, "Extension %": 32.08, "Overextended": true, "Drawdown %": -0.72, "Stop Triggered": false, "Hard Stop Triggered": false, "Hard Stop %": 12.0, "Stop Threshold": 16.03, "Vol Surge": 0.69, "Acceleration": true, "Breakout": false, "Near High": true, "Dollar Volume": 202741395.8506714, "Leveraged": false, "TV_Oscillators": "NEUTRAL", "TV_MovingAverages": "BUY", "TV_RSI": 81.29, "TV_MACD": 0.0673, "Entry Quality": "MOMENTUM", "Short Interest": 0.0734, "Days To Cover": 0, "Squeeze Score": 0, "Score": 297.24, "Name": "Oscar Health, Inc.", "osc_buy": 3, "osc_sell": 2, "osc_neutral": 1, "ma_buy": 8, "ma_sell": 0, "ma_neutral": 0}, {"Ticker": "CBRL", "Price": 46.31, "ATR": 3.16, "ATR %": 6.82, "Today %": 0.41, "3D %": -2.18, "5D %": 5.85, "15D %": 35.53, "13W %": 74.65, "MA20": 39.14, "MA50": 33.76, "MA200": 32.91, "MA50 Rising": true, "Above 200MA": true, "Above MA20": true, "Trend Quality": true, "Extension %": 37.19, "Overextended": true, "Drawdown %": -2.18, "Stop Triggered": false, "Hard Stop Triggered": false, "Hard Stop %": 12.0, "Stop Threshold": 16.67, "Vol Surge": 0.58, "Acceleration": false, "Breakout": false, "Near High": false, "Dollar Volume": 78085956.14058495, "Leveraged": false, "TV_Oscillators": "NEUTRAL", "TV_MovingAverages": "BUY", "TV_RSI": 76.03, "TV_MACD": 0.6883, "Entry Quality": "MOMENTUM", "Short Interest": 0.45049998, "Days To Cover": 0, "Squeeze Score": 0, "Score": 86.08, "Name": "Cracker Barrel Old Country Stor", "osc_buy": 3, "osc_sell": 2, "osc_neutral": 1, "ma_buy": 8, "ma_sell": 0, "ma_neutral": 0}, {"Ticker": "REPL", "Price": 11.78, "ATR": 0.94, "ATR %": 8.01, "Today %": 5.41, "3D %": 15.65, "5D %": 34.23, "15D %": 32.86, "13W %": 63.23, "MA20": 8.75, "MA50": 5.49, "MA200": 7.11, "MA50 Rising": true, "Above 200MA": true, "Above MA20": true, "Trend Quality": true, "Extension %": 114.72, "Overextended": true, "Drawdown %": 0.0, "Stop Triggered": false, "Hard Stop Triggered": false, "Hard Stop %": 12.0, "Stop Threshold": 20.03, "Vol Surge": 0.41, "Acceleration": false, "Breakout": false, "Near High": true, "Dollar Volume": 73669575.52415313, "Leveraged": false, "TV_Oscillators": "NEUTRAL", "TV_MovingAverages": "BUY", "TV_RSI": 71.32, "TV_MACD": 0.1595, "Entry Quality": "MOMENTUM", "Short Interest": 0.5633, "Days To Cover": 0, "Squeeze Score": 0, "Score": 169.81, "Name": "Replimune Group, Inc.", "osc_buy": 3, "osc_sell": 2, "osc_neutral": 1, "ma_buy": 8, "ma_sell": 0, "ma_neutral": 0}, {"Ticker": "BWIN", "Price": 25.4, "ATR": 1.55, "ATR %": 6.09, "Today %": 7.99, "3D %": 25.49, "5D %": 35.9, "15D %": 30.39, "13W %": 20.44, "MA20": 19.66, "MA50": 21.2, "MA200": 23.54, "MA50 Rising": false, "Above 200MA": true, "Above MA20": true, "Trend Quality": false, "Extension %": 19.81, "Overextended": false, "Drawdown %": -4.65, "Stop Triggered": false, "Hard Stop Triggered": false, "Hard Stop %": 12.0, "Stop Threshold": 14.51, "Vol Surge": 1.6, "Acceleration": true, "Breakout": false, "Near High": true, "Dollar Volume": 50436649.70251751, "Leveraged": false, "TV_Oscillators": "NEUTRAL", "TV_MovingAverages": "NEUTRAL", "TV_RSI": 71.42, "TV_MACD": 0.6879, "Entry Quality": "MOMENTUM", "Short Interest": 0.1442, "Days To Cover": 0, "Squeeze Score": 0, "Score": 215.51, "Name": "The Baldwin Insurance Group, In", "osc_buy": 3, "osc_sell": 3, "osc_neutral": 0, "ma_buy": 5, "ma_sell": 3, "ma_neutral": 0}, {"Ticker": "TVTX", "Price": 55.65, "ATR": 2.44, "ATR %": 4.39, "Today %": 0.99, "3D %": 0.92, "5D %": 4.26, "15D %": 29.55, "13W %": 104.24, "MA20": 49.14, "MA50": 44.81, "MA200": 33.97, "MA50 Rising": true, "Above 200MA": true, "Above MA20": true, "Trend Quality": true, "Extension %": 24.2, "Overextended": true, "Drawdown %": 0.0, "Stop Triggered": false, "Hard Stop Triggered": false, "Hard Stop %": 12.0, "Stop Threshold": 10.97, "Vol Surge": 1.1, "Acceleration": false, "Breakout": true, "Near High": true, "Dollar Volume": 124840548.67307281, "Leveraged": false, "TV_Oscillators": "NEUTRAL", "TV_MovingAverages": "BUY", "TV_RSI": 85.23, "TV_MACD": 0.5983, "Entry Quality": "MOMENTUM", "Short Interest": 0.19860001, "Days To Cover": 0, "Squeeze Score": 0, "Score": 300, "Name": "Travere Therapeutics, Inc.", "osc_buy": 3, "osc_sell": 3, "osc_neutral": 0, "ma_buy": 8, "ma_sell": 0, "ma_neutral": 0}, {"Ticker": "GEO", "Price": 30.14, "ATR": 1.14, "ATR %": 3.79, "Today %": 1.58, "3D %": 2.94, "5D %": 5.27, "15D %": 28.91, "13W %": 80.37, "MA20": 26.3, "MA50": 22.66, "MA200": 18.4, "MA50 Rising": true, "Above 200MA": true, "Above MA20": true, "Trend Quality": true, "Extension %": 33.0, "Overextended": true, "Drawdown %": 0.0, "Stop Triggered": false, "Hard Stop Triggered": false, "Hard Stop %": 12.0, "Stop Threshold": 9.48, "Vol Surge": 1.23, "Acceleration": false, "Breakout": true, "Near High": true, "Dollar Volume": 62995972.897296906, "Leveraged": false, "TV_Oscillators": "NEUTRAL", "TV_MovingAverages": "BUY", "TV_RSI": 97.47, "TV_MACD": 0.1877, "Entry Quality": "MOMENTUM", "Short Interest": 0.098500006, "Days To Cover": 0, "Squeeze Score": 0, "Score": 292.32, "Name": "Geo Group Inc (The) REIT", "osc_buy": 3, "osc_sell": 2, "osc_neutral": 1, "ma_buy": 8, "ma_sell": 0, "ma_neutral": 0}, {"Ticker": "TH", "Price": 20.57, "ATR": 0.77, "ATR %": 3.74, "Today %": 2.11, "3D %": 2.01, "5D %": 8.12, "15D %": 21.33, "13W %": 114.0, "MA20": 17.99, "MA50": 16.75, "MA200": 10.31, "MA50 Rising": true, "Above 200MA": true, "Above MA20": true, "Trend Quality": true, "Extension %": 22.76, "Overextended": true, "Drawdown %": 0.0, "Stop Triggered": false, "Hard Stop Triggered": false, "Hard Stop %": 12.0, "Stop Threshold": 9.35, "Vol Surge": 0.82, "Acceleration": false, "Breakout": false, "Near High": true, "Dollar Volume": 31594234.478978537, "Leveraged": false, "TV_Oscillators": "NEUTRAL", "TV_MovingAverages": "BUY", "TV_RSI": 79.66, "TV_MACD": 0.254, "Entry Quality": "MOMENTUM", "Short Interest": 0.1001, "Days To Cover": 0, "Squeeze Score": 0, "Score": 300, "Name": "Target Hospitality Corp.", "osc_buy": 3, "osc_sell": 3, "osc_neutral": 0, "ma_buy": 7, "ma_sell": 1, "ma_neutral": 0}, {"Ticker": "XBI", "Price": 147.82, "ATR": 4.38, "ATR %": 2.96, "Today %": 1.34, "3D %": 5.15, "5D %": 9.32, "15D %": 15.81, "13W %": 23.72, "MA20": 134.61, "MA50": 133.91, "MA200": 121.19, "MA50 Rising": true, "Above 200MA": true, "Above MA20": true, "Trend Quality": true, "Extension %": 10.38, "Overextended": false, "Drawdown %": 0.0, "Stop Triggered": false, "Hard Stop Triggered": false, "Hard Stop %": 12.0, "Stop Threshold": 7.4, "Vol Surge": 1.25, "Acceleration": false, "Breakout": true, "Near High": true, "Dollar Volume": 1317765669.319803, "Leveraged": false, "TV_Oscillators": "NEUTRAL", "TV_MovingAverages": "BUY", "TV_RSI": 77.03, "TV_MACD": 1.7326, "Entry Quality": "MOMENTUM", "Short Interest": 0, "Days To Cover": 0, "Squeeze Score": 0, "Score": 232.98, "Name": "State Street SPDR S&P Biotech E", "osc_buy": 3, "osc_sell": 3, "osc_neutral": 0, "ma_buy": 7, "ma_sell": 1, "ma_neutral": 0}, {"Ticker": "ALKS", "Price": 47.5, "ATR": 1.69, "ATR %": 3.55, "Today %": 3.22, "3D %": 5.58, "5D %": 7.73, "15D %": 14.96, "13W %": 61.62, "MA20": 43.07, "MA50": 38.35, "MA200": 32.35, "MA50 Rising": true, "Above 200MA": true, "Above MA20": true, "Trend Quality": true, "Extension %": 23.86, "Overextended": true, "Drawdown %": 0.0, "Stop Triggered": false, "Hard Stop Triggered": false, "Hard Stop %": 12.0, "Stop Threshold": 8.88, "Vol Surge": 1.25, "Acceleration": true, "Breakout": true, "Near High": true, "Dollar Volume": 109785640.875, "Leveraged": false, "TV_Oscillators": "NEUTRAL", "TV_MovingAverages": "BUY", "TV_RSI": 78.72, "TV_MACD": 0.1188, "Entry Quality": "MOMENTUM", "Short Interest": 0.1447, "Days To Cover": 0, "Squeeze Score": 0, "Score": 300, "Name": "Alkermes plc", "osc_buy": 3, "osc_sell": 3, "osc_neutral": 0, "ma_buy": 8, "ma_sell": 0, "ma_neutral": 0}, {"Ticker": "RLAY", "Price": 17.39, "ATR": 0.99, "ATR %": 5.69, "Today %": 0.64, "3D %": 9.51, "5D %": 15.55, "15D %": 10.76, "13W %": 81.15, "MA20": 14.81, "MA50": 14.27, "MA200": 9.44, "MA50 Rising": true, "Above 200MA": true, "Above MA20": true, "Trend Quality": true, "Extension %": 21.87, "Overextended": true, "Drawdown %": 0.0, "Stop Triggered": false, "Hard Stop Triggered": false, "Hard Stop %": 12.0, "Stop Threshold": 14.23, "Vol Surge": 1.1, "Acceleration": true, "Breakout": true, "Near High": true, "Dollar Volume": 67556658.32540666, "Leveraged": false, "TV_Oscillators": "NEUTRAL", "TV_MovingAverages": "BUY", "TV_RSI": 61.66, "TV_MACD": 0.3017, "Entry Quality": "MOMENTUM", "Short Interest": 0.1839, "Days To Cover": 0, "Squeeze Score": 0, "Score": 293.68, "Name": "Relay Therapeutics, Inc.", "osc_buy": 3, "osc_sell": 2, "osc_neutral": 1, "ma_buy": 7, "ma_sell": 1, "ma_neutral": 0}, {"Ticker": "MANE", "Price": 105.99, "ATR": 6.97, "ATR %": 6.58, "Today %": 3.11, "3D %": 12.91, "5D %": 16.54, "15D %": 7.95, "13W %": 61.74, "MA20": 97.36, "MA50": 95.4, "MA200": null, "MA50 Rising": true, "Above 200MA": false, "Above MA20": true, "Trend Quality": false, "Extension %": 11.11, "Overextended": false, "Drawdown %": -7.67, "Stop Triggered": false, "Hard Stop Triggered": false, "Hard Stop %": 12.0, "Stop Threshold": 15.18, "Vol Surge": 1.12, "Acceleration": true, "Breakout": false, "Near High": true, "Dollar Volume": 53935511.77692871, "Leveraged": false, "TV_Oscillators": "NEUTRAL", "TV_MovingAverages": "BUY", "TV_RSI": 57.97, "TV_MACD": 0.4067, "Entry Quality": "BREAKOUT", "Short Interest": 0.086899996, "Days To Cover": 0, "Squeeze Score": 0, "Score": 90.95, "Name": "Veradermics, Incorporated", "osc_buy": 2, "osc_sell": 3, "osc_neutral": 1, "ma_buy": 6, "ma_sell": 1, "ma_neutral": 0}], "etfs": [{"Ticker": "LABU", "Price": 238.41, "ATR": 17.32, "ATR %": 7.26, "Today %": 3.65, "3D %": 15.25, "5D %": 29.13, "15D %": 50.74, "13W %": 72.12, "MA20": 184.52, "MA50": 185.75, "MA200": 153.74, "MA50 Rising": true, "Above 200MA": true, "Above MA20": true, "Trend Quality": true, "Extension %": 28.35, "Overextended": true, "Drawdown %": 0.0, "Stop Triggered": false, "Hard Stop Triggered": false, "Hard Stop %": 25.0, "Stop Threshold": 18.16, "Vol Surge": 1.06, "Acceleration": false, "Breakout": true, "Near High": true, "Dollar Volume": 159312740.5881317, "Leveraged": true, "TV_Oscillators": "NEUTRAL", "TV_MovingAverages": "BUY", "TV_RSI": 77.13, "TV_MACD": 7.3389, "Entry Quality": "MOMENTUM", "Short Interest": 0, "Days To Cover": 0, "Squeeze Score": 0, "Score": 300, "Name": "Direxion Daily S&P Biotech Bull", "osc_buy": 3, "osc_sell": 3, "osc_neutral": 0, "ma_buy": 6, "ma_sell": 2, "ma_neutral": 0}, {"Ticker": "WGMI", "Price": 71.8, "ATR": 5.46, "ATR %": 7.6, "Today %": -0.25, "3D %": -0.42, "5D %": 3.67, "15D %": 0.41, "13W %": 104.04, "MA20": 67.8, "MA50": 58.85, "MA200": 48.09, "MA50 Rising": true, "Above 200MA": true, "Above MA20": true, "Trend Quality": true, "Extension %": 22.01, "Overextended": true, "Drawdown %": -0.42, "Stop Triggered": false, "Hard Stop Triggered": false, "Hard Stop %": 12.0, "Stop Threshold": 18.92, "Vol Surge": 0.91, "Acceleration": false, "Breakout": false, "Near High": true, "Dollar Volume": 52892308.718112946, "Leveraged": false, "TV_Oscillators": "NEUTRAL", "TV_MovingAverages": "BUY", "TV_RSI": 50.42, "TV_MACD": 0.0821, "Entry Quality": "BREAKOUT", "Short Interest": 0, "Days To Cover": 0, "Squeeze Score": 0, "Score": 119.81, "Name": "CoinShares Bitcoin Mining ETF", "osc_buy": 2, "osc_sell": 1, "osc_neutral": 3, "ma_buy": 8, "ma_sell": 0, "ma_neutral": 0}]}